spacyex/__init__.py
spacyex-0.0.2.dist-info/METADATA
spacyex-0.0.2.dist-info/WHEEL
spacyex-0.0.2.dist-info/top_level.txt
spacyex-0.0.2.dist-info/RECORD
