Metadata-Version: 2.1
Name: spacyex
Version: 0.0.2
Summary: An extension for spaCy, making pattern matching as flexible as using regular expressions.
Home-page: https://github.com/wjbmattingly/spacyex
Author: William J.B. Mattingly
Classifier: Development Status :: 3 - Alpha
Classifier: Intended Audience :: Developers
Classifier: License :: OSI Approved :: MIT License
Classifier: Natural Language :: English
Classifier: Programming Language :: Python :: 3
Classifier: Programming Language :: Python :: 3.7
Classifier: Programming Language :: Python :: 3.8
Classifier: Programming Language :: Python :: 3.9
Classifier: Programming Language :: Python :: 3.10
Classifier: Operating System :: OS Independent
Requires-Python: >=3.7
Requires-Dist: spacy (>=3.5)
